dbt_log_parser/__init__.py
dbt_log_parser/machine.py
dbt_log_parser/parser.py
dbt_log_parser-0.2.1.dist-info/LICENSE
dbt_log_parser-0.2.1.dist-info/METADATA
dbt_log_parser-0.2.1.dist-info/WHEEL
dbt_log_parser-0.2.1.dist-info/entry_points.txt
dbt_log_parser-0.2.1.dist-info/top_level.txt
dbt_log_parser-0.2.1.dist-info/zip-safe
dbt_log_parser-0.2.1.dist-info/RECORD
