Metadata-Version: 2.1
Name: dbt-log-parser
Version: 0.2.1
Summary: Parse structured metadata from dbt logs
Home-page: https://github.com/mdzhang/dbt_log_parser
Author: Michelle Zhang
Author-email: zhang.michelle.d@gmail.com
License: MIT
Project-URL: Changelog, https://github.com/mdzhang/dbt_log_parser/blob/master/CHANGELOG.md
Keywords: dbt
Platform: UNKNOWN
Classifier: Development Status :: 1 - Planning
Classifier: Environment :: Console
Classifier: Intended Audience :: Developers
Classifier: License :: OSI Approved :: MIT License
Classifier: Operating System :: OS Independent
Classifier: Programming Language :: Python
Classifier: Programming Language :: Python :: 3.6
Classifier: Programming Language :: Python :: 3.7
Classifier: Programming Language :: Python :: 3.8
Classifier: Programming Language :: Python :: 3.9
Classifier: Programming Language :: Python :: 3 :: Only
Requires-Python: >=3.6
Requires-Dist: transitions (>=0.8.5)
Requires-Dist: dataclasses ; python_version < "3.7"
